django_shibauth_rit-1.1.0.dist-info/DESCRIPTION.rst
django_shibauth_rit-1.1.0.dist-info/METADATA
django_shibauth_rit-1.1.0.dist-info/RECORD
django_shibauth_rit-1.1.0.dist-info/WHEEL
django_shibauth_rit-1.1.0.dist-info/metadata.json
django_shibauth_rit-1.1.0.dist-info/top_level.txt
shibauth_rit/__init__.py
shibauth_rit/apps.py
shibauth_rit/backends.py
shibauth_rit/compat.py
shibauth_rit/conf.py
shibauth_rit/context_processors.py
shibauth_rit/middleware.py
shibauth_rit/urls.py
shibauth_rit/views.py
shibauth_rit/templates/shibauth_rit/base.html
shibauth_rit/templates/shibauth_rit/user_info.html
