Metadata-Version: 2.0
Name: django-shibauth-rit
Version: 1.1.0
Summary: Integrate Shibboleth Authentication with your RIT projects
Home-page: https://github.com/audiolion/django-shibauth-rit
Author: Ryan Castner
Author-email: castner.rr@gmail.com
License: MIT
Keywords: django-shibauth-rit
Platform: UNKNOWN
Classifier: Development Status :: 3 - Alpha
Classifier: Framework :: Django
Classifier: Framework :: Django :: 1.8
Classifier: Framework :: Django :: 1.9
Classifier: Framework :: Django :: 1.10
Classifier: Intended Audience :: Developers
Classifier: License :: OSI Approved :: BSD License
Classifier: Natural Language :: English
Classifier: Programming Language :: Python :: 2
Classifier: Programming Language :: Python :: 2.7
Classifier: Programming Language :: Python :: 3
Classifier: Programming Language :: Python :: 3.3
Classifier: Programming Language :: Python :: 3.4
Classifier: Programming Language :: Python :: 3.5
Requires-Dist: django-appconf (>=0.6)
Requires-Dist: requests (>=2.0.0)
